shakmaty_python_binding-0.1.5.dist-info/METADATA
shakmaty_python_binding-0.1.5.dist-info/WHEEL
shakmaty_python_binding/__init__.py
shakmaty_python_binding/__init__.pyi
shakmaty_python_binding/py.typed
shakmaty_python_binding/shakmaty_python_binding.cpython-311-x86_64-linux-gnu.so
shakmaty_python_binding-0.1.5.dist-info/RECORD
